__init__.py
_version.py
pyterp.cp312-win32.pyd
pyterp-0.3.1.dist-info/licenses/LICENSE
pyterp-0.3.1.dist-info/METADATA
pyterp-0.3.1.dist-info/WHEEL
pyterp-0.3.1.dist-info/top_level.txt
pyterp-0.3.1.dist-info/RECORD
