Metadata-Version: 2.4
Name: pyterp
Version: 0.3.1
Summary: A package for performing optimized k-NN IDW interpolation using C++.
Author-email: Jonathan Motta <jonathangmotta98@gmail.com>
Project-URL: Homepage, https://github.com/jgmotta98/PyTerp
Project-URL: Bug Tracker, https://github.com/jgmotta98/PyTerp/issues
Project-URL: Source Code, https://github.com/jgmotta98/PyTerp
Keywords: interpolation,k-NN,IDW,C++,parallel,numpy,performance
Classifier: Development Status :: 3 - Alpha
Classifier: Intended Audience :: Science/Research
Classifier: Intended Audience :: Developers
Classifier: Operating System :: OS Independent
Classifier: Topic :: Scientific/Engineering :: GIS
Classifier: Topic :: Scientific/Engineering :: Mathematics
Classifier: Topic :: Software Development :: Libraries :: Python Modules
Classifier: Programming Language :: Python :: 3.10
Classifier: Programming Language :: Python :: 3.11
Classifier: Programming Language :: Python :: 3.12
Classifier: Programming Language :: C++
Requires-Python: >=3.10
License-File: LICENSE
Requires-Dist: numpy>=2.0.0
Dynamic: license-file
